FinalProject/src/instructionmemory.v
//------------------------------------------------------------------------
// Instruction Memory
//   Positive edge triggered
//   dataOut always has the value mem[address]
//------------------------------------------------------------------------

module instructionmemory 
#(
    parameter cores = 1,
    parameter instructions = "one-core-memory.dat"
)
(
    input                       clk,
    input [31:0]                address,
    output reg [32*cores-1:0]   dataOut
);

    reg [32*cores-1:0] memory [2**10-1:0];

    initial $readmemb(instructions, memory);

    always @(posedge clk) begin
        dataOut <= memory[address];
    end

endmodule

FinalProject/test/instructionmemory.t.v
module test_instruction_module();

reg clk;
reg dutPass;
reg [31:0] inputaddress;
wire [63:0] two_output_instructions;

wire [31:0] one_output_instructions;

	instructionmemory #(1, "one-core-memory.dat") dut1(.clk(clk), 
																.address(inputaddress), 
																.dataOut(one_output_instructions));
	instructionmemory #(.cores(2),
		                .instructions("two-core-memory.dat"))
		                 dut2(.clk(clk), 
		                 	            .address(inputaddress), 
		                 	            .dataOut(two_output_instructions));
initial clk = 0;

always #1 clk = !clk;

initial begin 
		$dumpfile("instruction_module.t.vcd");
	    $dumpvars(0, test_instruction_module);
		dutPass = 1;
		inputaddress = 0;
		#4
	   	if(one_output_instructions !== 32'h00000000 || two_output_instructions !== 64'h0000000000000000)
	   	begin 
	   	dutPass =0;
	   	$display ("Woo FAIL at address %h", inputaddress);
	   	$display("%h", one_output_instructions);
	   	end
	   	inputaddress = inputaddress + 1;
		#2
	   	if(one_output_instructions !== 32'h11111111 || two_output_instructions !== 64'h1111111111111111)
	   	begin 
	   	dutPass =0;
	   	$display ("Woo FAIL at address %h", inputaddress);
	   	$display("%h", one_output_instructions);
	   	end
	   	inputaddress = inputaddress + 1;
	   	#2
	   	if(one_output_instructions !== 32'h22222222 || two_output_instructions !== 64'h2222222222222222)
	   	begin 
	   	dutPass =0;
	   	$display ("Woo FAIL at address %h", inputaddress);
	   	$display("%h", one_output_instructions);
	   	end
	   	inputaddress = inputaddress + 1;
	   	#2
	    if(one_output_instructions !== 32'h33333333 || two_output_instructions !== 64'h3333333333333333)
	   	begin 
	   	dutPass =0;
	   	$display ("Woo FAIL at address %h", inputaddress);
	   	$display("%h", one_output_instructions);
	   	end
	   	inputaddress = inputaddress + 1;
	   	#2
	   	if(one_output_instructions !== 32'h44444444 || two_output_instructions !== 64'h4444444444444444)
	   	begin 
	   	dutPass =0;
	   	$display ("Woo FAIL at address %h", inputaddress);
	   	$display("%h", one_output_instructions);
	   	end
	   	inputaddress = inputaddress + 1;
	   	#2
	   	if(one_output_instructions !== 32'h55555555 || two_output_instructions !== 64'h5555555555555555)
	   	begin 
	   	dutPass =0;
	   	$display ("Woo FAIL at address %h", inputaddress);
	   	$display("%h", one_output_instructions);
	   	end
	   	inputaddress = inputaddress + 1;
	   	#2
	   	if(one_output_instructions !== 32'h66666666 || two_output_instructions !== 64'h6666666666666666)
	   	begin 
	   	dutPass =0;
	   	$display ("Woo FAIL at address %h", inputaddress);
	   	$display("%h", one_output_instructions);
	   	end
	   	inputaddress = inputaddress + 1;
	   	#2
	    if(one_output_instructions !== 32'h77777777 || two_output_instructions !== 64'h7777777777777777)
	   	begin 
	   	dutPass =0;
	   	$display ("Woo FAIL at address %h", inputaddress);
	   	$display("%h", one_output_instructions);
	   	end
	   	inputaddress = inputaddress + 1;
	   	#2
	   	if(one_output_instructions !== 32'h88888888 || two_output_instructions !== 64'h8888888888888888)
	   	begin 
	   	dutPass =0;
	   	$display ("Woo FAIL at address %h", inputaddress);
	   	$display("%h", one_output_instructions);
	   	end
	   	inputaddress = inputaddress + 1;
	   	#2
	   	if(one_output_instructions !== 32'h99999999 || two_output_instructions !== 64'h9999999999999999)
	   	begin 
	   	dutPass =0;
	   	$display ("Woo FAIL at address %h", inputaddress);
	   	$display("%h", one_output_instructions);
	   	end
	   	inputaddress = inputaddress + 1;
	   	#2
	   	if(one_output_instructions !== 32'haaaaaaaa || two_output_instructions !== 64'haaaaaaaaaaaaaaaa)
	   	begin 
	   	dutPass =0;
	   	$display ("Woo FAIL at address %h", inputaddress);
	   	$display("%h", one_output_instructions);
	   	end
	   	inputaddress = inputaddress + 1;
	   	#2
	    if(one_output_instructions !== 32'hbbbbbbbb || two_output_instructions !== 64'hbbbbbbbbbbbbbbbb)
	   	begin 
	   	dutPass =0;
	   	$display ("Woo FAIL at address %h", inputaddress);
	   	$display("%h", one_output_instructions);
	   	end
	   	inputaddress = inputaddress + 1;
	   	#2
	   	if(one_output_instructions !== 32'hcccccccc || two_output_instructions !== 64'hcccccccccccccccc)
	   	begin 
	   	dutPass =0;
	   	$display ("Woo FAIL at address %h", inputaddress);
	   	$display("%h", one_output_instructions);
	   	end
	   	inputaddress = inputaddress + 1;
	   	#2
	    if(one_output_instructions !== 32'hdddddddd || two_output_instructions !== 64'hdddddddddddddddd)
	   	begin 
	   	dutPass =0;
	   	$display ("Woo FAIL at address %h", inputaddress);
	   	$display("%h", one_output_instructions);
	   	end
	   	inputaddress = inputaddress + 1;
	   	#2
	   	if(one_output_instructions !== 32'heeeeeeee || two_output_instructions !== 64'heeeeeeeeeeeeeeee)
	   	begin 
	   	dutPass =0;
	   	$display ("Woo FAIL at address %h", inputaddress);
	   	$display("%h", one_output_instructions);
	   	end
	   	inputaddress = inputaddress + 1;
	   	#2
	    if(one_output_instructions !== 32'hffffffff || two_output_instructions !== 64'hffffffffffffffff)
	   	begin 
	   	dutPass =0;
	   	$display ("Woo FAIL at address %h", inputaddress);
	   	$display("%h", one_output_instructions);
	   	end
	   	inputaddress = inputaddress + 1;
	   	#2

	   	if(dutPass == 1 )
	   	$display("PASS :D");
	   	else   	begin 
	   	$display("FAIL :(");
	   	end
	    $finish;

end 



endmodule

FinalProject/test/instruction_module.t.vcd
$date
	Tue Dec  1 23:05:26 2015
$end
$version
	Icarus Verilog
$end
$timescale
	1s
$end
$scope module test_instruction_module $end
$var wire 32 ! one_output_instructions [31:0] $end
$var wire 64 " two_output_instructions [63:0] $end
$var reg 1 # clk $end
$var reg 1 $ dutPass $end
$var reg 32 % inputaddress [31:0] $end
$scope module dut1 $end
$var wire 32 & address [31:0] $end
$var wire 1 ' clk $end
$var reg 32 ( dataOut [31:0] $end
$upscope $end
$scope module dut2 $end
$var wire 32 ) address [31:0] $end
$var wire 1 ' clk $end
$var reg 64 * dataOut [63:0] $end
$upscope $end
$upscope $end
$enddefinitions $end
#0
$dumpvars
bx *
b0 )
bx (
0'
b0 &
b0 %
1$
0#
bx "
bx !
$end
#1
b0 (
b0 !
b0 *
b0 "
1#
1'
#2
0#
0'
#3
1#
1'
#4
0#
0'
b1 %
b1 &
b1 )
#5
b10001000100010001000100010001 (
b10001000100010001000100010001 !
b1000100010001000100010001000100010001000100010001000100010001 *
b1000100010001000100010001000100010001000100010001000100010001 "
1#
1'
#6
0#
0'
b10 %
b10 &
b10 )
#7
b10001000100010001000100010001000100010001000100010001000100010 *
b10001000100010001000100010001000100010001000100010001000100010 "
b100010001000100010001000100010 (
b100010001000100010001000100010 !
1#
1'
#8
0#
0'
b11 %
b11 &
b11 )
#9
b110011001100110011001100110011 (
b110011001100110011001100110011 !
b11001100110011001100110011001100110011001100110011001100110011 *
b11001100110011001100110011001100110011001100110011001100110011 "
1#
1'
#10
0#
0'
b100 %
b100 &
b100 )
#11
b100010001000100010001000100010001000100010001000100010001000100 *
b100010001000100010001000100010001000100010001000100010001000100 "
b1000100010001000100010001000100 (
b1000100010001000100010001000100 !
1#
1'
#12
0#
0'
b101 %
b101 &
b101 )
#13
b1010101010101010101010101010001 (
b1010101010101010101010101010001 !
b101010101010101010101010101010101010101010101010101010101010101 *
b101010101010101010101010101010101010101010101010101010101010101 "
1#
1'
#14
0#
0'
b110 %
b110 &
b110 )
0$
#15
b110011001100110011001100110011001100110011001100110011001100110 *
b110011001100110011001100110011001100110011001100110011001100110 "
b1100110011001100110011001100110 (
b1100110011001100110011001100110 !
1#
1'
#16
0#
0'
b111 %
b111 &
b111 )
#17
b1110111011101110111011101110111 (
b1110111011101110111011101110111 !
b111011101110111011101110111011101110111011101110111011101110111 *
b111011101110111011101110111011101110111011101110111011101110111 "
1#
1'
#18
0#
0'
b1000 %
b1000 &
b1000 )
#19
b1000100010001000100010001000100010001000100010001000100010001000 *
b1000100010001000100010001000100010001000100010001000100010001000 "
b10001000100010001000100010001000 (
b10001000100010001000100010001000 !
1#
1'
#20
0#
0'
b1001 %
b1001 &
b1001 )
#21
b10011001100110011001100110011001 (
b10011001100110011001100110011001 !
b1001100110011001100110011001100110011001100110011001100110011001 *
b1001100110011001100110011001100110011001100110011001100110011001 "
1#
1'
#22
0#
0'
b1010 %
b1010 &
b1010 )
#23
b1010101010101010101010101010101010101010101010101010101010101010 *
b1010101010101010101010101010101010101010101010101010101010101010 "
b10101010101010101010101010101010 (
b10101010101010101010101010101010 !
1#
1'
#24
0#
0'
b1011 %
b1011 &
b1011 )
#25
b10111011101110111011101110111011 (
b10111011101110111011101110111011 !
b1011101110111011101110111011101110111011101110111011101110111011 *
b1011101110111011101110111011101110111011101110111011101110111011 "
1#
1'
#26
0#
0'
b1100 %
b1100 &
b1100 )
#27
b1100110011001100110011001100110011001100110011001100110011001100 *
b1100110011001100110011001100110011001100110011001100110011001100 "
b11001100110011001100110011001100 (
b11001100110011001100110011001100 !
1#
1'
#28
0#
0'
b1101 %
b1101 &
b1101 )
#29
b11011101110111011101110111011101 (
b11011101110111011101110111011101 !
b1101110111011101110111011101110111011101110111011101110111011101 *
b1101110111011101110111011101110111011101110111011101110111011101 "
1#
1'
#30
0#
0'
b1110 %
b1110 &
b1110 )
#31
b1110111011101110111011101110111011101110111011101110111011101110 *
b1110111011101110111011101110111011101110111011101110111011101110 "
b11101110111011101110111011101110 (
b11101110111011101110111011101110 !
1#
1'
#32
0#
0'
b1111 %
b1111 &
b1111 )
#33
b11111111111111111111111111111111 (
b11111111111111111111111111111111 !
b1111111111111111111111111111111111111111111111111111111111111111 *
b1111111111111111111111111111111111111111111111111111111111111111 "
1#
1'
#34
0#
0'
b10000 %
b10000 &
b10000 )
#35
bx *
bx "
bx (
bx !
1#
1'
