FinalProject/src/instructionmemory.v
//------------------------------------------------------------------------
// Instruction Memory
//   Positive edge triggered
//   dataOut always has the value mem[address]
//------------------------------------------------------------------------

module instructionmemory 
#(
    parameter cores = 1,
    parameter instructions = "one-core-memory.dat"
)
(
    input                       clk,
    input [31:0]                address,
    output reg [32*cores-1:0]   dataOut
);

    reg [32*cores-1:0] memory [2**10-1:0];

    initial $readmemb(instructions, memory);

    always @(posedge clk) begin
        dataOut <= memory[address];
    end

endmodule

FinalProject/test/instructionmemory.t.v
module test_instruction_module();

reg clk;
reg [31:0] inputaddress;
wire [63:0] two_output_instructions;

wire [31:0] one_output_instructions;

	instructionmemory #(1, "one-core-memory.dat") dut1(.clk(clk), 
																.address(inputaddress), 
																.dataOut(one_output_instructions));
	instructionmemory #(.cores(2),
		                .instructions("two-core-memory.dat"))
		                 dut2(.clk(clk), 
		                 	            .address(inputaddress), 
		                 	            .dataOut(two_output_instructions));
initial clk = 0;
always #1 clk = !clk;

initial begin 

		$dumpfile("instruction_module.t.vcd");
	    $dumpvars(0, test_instruction_module);

	    inputaddress = 0;
	    #4;
	    inputaddress = 1;
	    #4;
	    inputaddress = 2;
	    #4
	    inputaddress = 3;
	    #4
	    

	    $finish;

end 



endmodule

FinalProject/test/instruction_module.t.vcd
$date
	Tue Dec  1 22:23:15 2015
$end
$version
	Icarus Verilog
$end
$timescale
	1s
$end
$scope module test_instruction_module $end
$var wire 32 ! one_output_instructions [31:0] $end
$var wire 64 " two_output_instructions [63:0] $end
$var reg 1 # clk $end
$var reg 32 $ inputaddress [31:0] $end
$scope module dut1 $end
$var wire 32 % address [31:0] $end
$var wire 1 & clk $end
$var reg 32 ' dataOut [31:0] $end
$upscope $end
$scope module dut2 $end
$var wire 32 ( address [31:0] $end
$var wire 1 & clk $end
$var reg 64 ) dataOut [63:0] $end
$upscope $end
$upscope $end
$enddefinitions $end
#0
$dumpvars
bx )
b0 (
bx '
0&
b0 %
b0 $
0#
bx "
bx !
$end
#1
b10001100000001000010000000000100 '
b10001100000001000010000000000100 !
b1010101010101010101010101010101010101010101010101010101010101010 )
b1010101010101010101010101010101010101010101010101010101010101010 "
1#
1&
#2
0#
0&
#3
1#
1&
#4
0#
0&
b1 $
b1 %
b1 (
#5
b10001100000001010010000000001000 '
b10001100000001010010000000001000 !
b1011101110111011101110111011101110111011101110111011101110111011 )
b1011101110111011101110111011101110111011101110111011101110111011 "
1#
1&
#6
0#
0&
#7
1#
1&
#8
0#
0&
b10 $
b10 %
b10 (
#9
b1100000000000000000000000111 '
b1100000000000000000000000111 !
b1100110011001100110011001100110011001100110011001100110011001100 )
b1100110011001100110011001100110011001100110011001100110011001100 "
1#
1&
#10
0#
0&
#11
1#
1&
#12
0#
0&
b11 $
b11 %
b11 (
#13
b11000001000000000100000 '
b11000001000000000100000 !
b1101110111011101110111011101110111011101110111011101110111011101 )
b1101110111011101110111011101110111011101110111011101110111011101 "
1#
1&
